keep/NoteGrid.py
keep/__init__.py
keep/__main__.py
keep/keep.py
keep_cli-0.1.15.dist-info/LICENSE
keep_cli-0.1.15.dist-info/METADATA
keep_cli-0.1.15.dist-info/WHEEL
keep_cli-0.1.15.dist-info/entry_points.txt
keep_cli-0.1.15.dist-info/top_level.txt
keep_cli-0.1.15.dist-info/RECORD
