Metadata-Version: 2.1
Name: keep-cli
Version: 0.1.15
Summary: Keep-cli is a cli Google Keep client. You can add, delete, and manage your Google Keep notes.
Home-page: https://github.com/zack-ashen/keep-cli
Author: Zachary Ashen
Author-email: zachary.h.a@gmail.com
License: MIT
Keywords: cli google notes notetaking todo google-keep keep keep-cli
Platform: UNKNOWN
Classifier: Development Status :: 3 - Alpha
Classifier: Intended Audience :: Developers
Classifier: Environment :: Console
Classifier: License :: OSI Approved :: MIT License
Classifier: Programming Language :: Python :: 3.7
Classifier: Programming Language :: Python :: 3.8
Requires-Python: >=3.7
Requires-Dist: gkeepapi (>=0.11.16)
Requires-Dist: pyfiglet (>=0.8.post1)
Requires-Dist: PyInquirer (>=1.0.3)
Requires-Dist: argparse (>=1.4.0)
Requires-Dist: keyring (>=21.2.1)
Requires-Dist: keyrings.alt (>=3.4.0)
